dmario24_cmd/__init__.py
dmario24_cmd/cmd.py
dmario24_cmd-0.1.1.dist-info/METADATA
dmario24_cmd-0.1.1.dist-info/WHEEL
dmario24_cmd-0.1.1.dist-info/entry_points.txt
dmario24_cmd-0.1.1.dist-info/top_level.txt
dmario24_cmd-0.1.1.dist-info/RECORD
