Metadata-Version: 2.1
Name: dmario24_cmd
Version: 0.1.1
Summary: Default template for PDM package
Author-email: dMario24 <data.mario24@gmail.com>
License: MIT
Requires-Python: >=3.9
Requires-Dist: dmario24-lotto >=0.2.0
